screcode/__init__.py
screcode/screcode.py
screcode-2.2.0.dist-info/METADATA
screcode-2.2.0.dist-info/WHEEL
screcode-2.2.0.dist-info/RECORD
