Metadata-Version: 2.3
Name: screcode
Version: 2.2.0
Summary: RECODE - resolution of the curse of dimensionality in single-cell data analysis
Author: Yusuke Imoto
Requires-Python: >=3.8
Classifier: Programming Language :: Python :: 3
Classifier: Programming Language :: Python :: 3.8
Classifier: Programming Language :: Python :: 3.9
Classifier: Programming Language :: Python :: 3.10
Classifier: Programming Language :: Python :: 3.11
Classifier: Programming Language :: Python :: 3.12
Classifier: Programming Language :: Python :: 3.13
Requires-Dist: adjustText (>=0.7)
Requires-Dist: anndata (>=0.8.0)
Requires-Dist: datetime (>=4.0)
Requires-Dist: matplotlib (>=3.4.3)
Requires-Dist: numpy (>=1.20)
Requires-Dist: pandas (>=2.0.0)
Requires-Dist: scanpy (>=1.9.3)
Requires-Dist: scikit-learn (>=0.24)
Requires-Dist: scipy (>=1.8.1,<2.0.0)
Requires-Dist: seaborn (>=0.11.2)
Project-URL: Documentation, https://yusuke-imoto-lab.github.io/RECODE/
Project-URL: Repository, https://github.com/yusuke-imoto-lab/RECODE
